Artist/__init__.py
Artist/base_programs.py
Artist/dataset.py
Artist/general_trainer.py
Artist/progressive_trainer.py
Artist/models/base.py
Artist/models/dcgan.py
Artist/models/progressive_gan.py
Artist_Engineering_Geek-0.1.0.dist-info/LICENSE
Artist_Engineering_Geek-0.1.0.dist-info/METADATA
Artist_Engineering_Geek-0.1.0.dist-info/WHEEL
Artist_Engineering_Geek-0.1.0.dist-info/top_level.txt
Artist_Engineering_Geek-0.1.0.dist-info/RECORD
