Metadata-Version: 2.1
Name: Artist-Engineering-Geek
Version: 0.1.0
Summary: A bunch of GANs and data downloaders to make a custom AI artist
Home-page: https://github.com/Fatima-x-Nikhil/Artist
Author: Nikhil Melgiri
Author-email: nmelgiri@uwaterloo.ca
License: UNKNOWN
Project-URL: Bug Tracker, https://github.com/Fatima-x-Nikhil/Artist/issues
Platform: UNKNOWN
Classifier: Programming Language :: Python :: 3
Classifier: License :: OSI Approved :: MIT License
Classifier: Operating System :: OS Independent
Requires-Python: >=3.6
Requires-Dist: torch
Requires-Dist: torchvision
Requires-Dist: matplotlib
Requires-Dist: Pillow
Requires-Dist: pytorch-lightning
Requires-Dist: numpy
Requires-Dist: tqdm
Requires-Dist: requests
